[{"city": "Puerto Quellon", "id": 3874943}, {"city": "Nacimiento", "id": 3879123}, {"city": "El Tabo", "id": 3890338}, {"city": "Regi\u00f3n del Libertador General Bernardo O\u2019Higgins", "id": 3883281}, {"city": "Lo Moscoso", "id": 3882585}, {"city": "Bar\u00f3n", "id": 3898749}, {"city": "Regi\u00f3n de Los Lagos", "id": 3881974}, {"city": "Las Animas", "id": 6458708}, {"city": "Puerto Montt", "id": 3874960}, {"city": "Las Condes", "id": 3884448}, {"city": "Regi\u00f3n del Maule", "id": 3880306}, {"city": "Talca", "id": 3870294}, {"city": "Concepcion", "id": 3893894}, {"city": "Regi\u00f3n de Antofagasta", "id": 3899537}, {"city": "Chuquicamata", "id": 3894689}, {"city": "Lo Contador", "id": 3882722}, {"city": "Providencia", "id": 3875139}, {"city": "Regi\u00f3n de la Araucan\u00eda", "id": 3899463}, {"city": "Maip\u00fa", "id": 3880980}, {"city": "Huilco", "id": 3887555}, {"city": "Valdivia", "id": 3868707}, {"city": "San Antonio", "id": 3872395}, {"city": "Puente Alto", "id": 3875024}, {"city": "Melipilla", "id": 3880107}, {"city": "La Union", "id": 3883629}, {"city": "Iquique", "id": 3887127}, {"city": "El Monte", "id": 3890949}, {"city": "Cauquenes", "id": 3896105}, {"city": "Cartagena", "id": 3896433}, {"city": "Canete", "id": 3896924}, {"city": "La Pintana", "id": 7281017}, {"city": "Lo Prado", "id": 7281020}, {"city": "Barrio Brazil", "id": 7648389}, {"city": "Achupallas", "id": 3900687}, {"city": "Valparaiso", "id": 3868626}, {"city": "Tocopilla", "id": 3869716}, {"city": "San Vicente", "id": 3871286}, {"city": "Santa Cruz", "id": 3871616}, {"city": "San Bernardo", "id": 3872348}, {"city": "Frutillar", "id": 3889263}, {"city": "Regi\u00f3n de Arica y Parinacota", "id": 6693562}, {"city": "Provincia de Arica", "id": 3899358}, {"city": "Republic of Chile", "id": 3895114}, {"city": "Regi\u00f3n de Magallanes y de la Ant\u00e1rtica Chilena", "id": 4036650}, {"city": "R\u00edo de los Ciervos", "id": 3873132}, {"city": "Regi\u00f3n de Los R\u00edos", "id": 6693563}, {"city": "Lleco", "id": 3882922}, {"city": "Regi\u00f3n del Biob\u00edo", "id": 3898380}, {"city": "Chillan", "id": 3895088}, {"city": "Caletones", "id": 3897287}, {"city": "Regi\u00f3n Metropolitana de Santiago", "id": 3873544}, {"city": "Los Maitenes", "id": 3881849}, {"city": "La Ermita", "id": 3886043}, {"city": "Villa Paulina", "id": 3868168}, {"city": "Regi\u00f3n de Valpara\u00edso", "id": 3868621}, {"city": "Placilla de Pe\u00f1uelas", "id": 3875684}, {"city": "Limache", "id": 3883214}, {"city": "Quinquimo", "id": 3874005}, {"city": "Regi\u00f3n de Atacama", "id": 3899191}, {"city": "Mirador", "id": 3879750}, {"city": "Temuco", "id": 3870011}, {"city": "Los Andes", "id": 3882434}, {"city": "Talcahuano", "id": 3870282}, {"city": "Calama", "id": 3897347}, {"city": "Antofagasta", "id": 3899539}, {"city": "El Rosal", "id": 3890484}, {"city": "Regi\u00f3n de Coquimbo", "id": 3893623}, {"city": "La Serena", "id": 3884373}, {"city": "Hacienda La Calera", "id": 3888214}, {"city": "Provincia de Valpara\u00edso", "id": 3868623}, {"city": "Quilpue", "id": 3874096}, {"city": "San Felipe", "id": 3872255}, {"city": "Coquimbo", "id": 3893629}, {"city": "Los Angeles", "id": 3882428}, {"city": "San Fernando", "id": 3872240}, {"city": "Copiapo", "id": 3893656}, {"city": "Punta Arenas", "id": 3874787}, {"city": "Osorno", "id": 3877949}, {"city": "Angol", "id": 3899629}, {"city": "Pur\u00e9n", "id": 3874612}, {"city": "Villarrica", "id": 3868158}, {"city": "El Manzano", "id": 3891085}, {"city": "Linares", "id": 3883167}, {"city": "Diego de Almagro", "id": 3892454}, {"city": "Pe\u00f1alol\u00e9n", "id": 3876682}, {"city": "Colina", "id": 3894242}, {"city": "Vitacura", "id": 3868044}, {"city": "Quilicura", "id": 3874212}, {"city": "Macul", "id": 3881068}, {"city": "Conc\u00f3n", "id": 3893865}, {"city": "Constitucion", "id": 3893726}, {"city": "Miramar", "id": 3879708}, {"city": "Ancud", "id": 3899695}, {"city": "Buin", "id": 3897774}, {"city": "Paine", "id": 3877739}, {"city": "Rancagua", "id": 3873775}, {"city": "Lampa", "id": 3885273}, {"city": "Regi\u00f3n Ais\u00e9n del General Carlos Ib\u00e1\u00f1ez del Campo", "id": 3900333}, {"city": "Coihaique", "id": 3894426}, {"city": "Panguipulli", "id": 3877348}, {"city": "Villa Alemana", "id": 3868192}, {"city": "Cabildo", "id": 3897595}, {"city": "Puerto Varas", "id": 3874930}, {"city": "Coronel", "id": 3893532}, {"city": "Chiguayante", "id": 3895138}, {"city": "Quillota", "id": 3874119}, {"city": "Lota", "id": 3881276}, {"city": "Traiguen", "id": 3869381}, {"city": "Penco", "id": 3876664}, {"city": "Penaflor", "id": 3876685}, {"city": "La Laja", "id": 3885509}, {"city": "Curico", "id": 3892870}, {"city": "Parral", "id": 3877146}, {"city": "Talagante", "id": 3870306}, {"city": "Yumbel", "id": 3867625}, {"city": "Arauco", "id": 3899462}, {"city": "San Francisco de Limache", "id": 3872206}, {"city": "Llaillay", "id": 3883035}, {"city": "San Javier", "id": 3872154}, {"city": "Chimbarongo", "id": 3895061}, {"city": "Tambillo", "id": 3870212}, {"city": "Ovalle", "id": 3877918}, {"city": "Purranque", "id": 3874579}, {"city": "Rio Bueno", "id": 3873145}, {"city": "Loncoche", "id": 3882582}, {"city": "San Jos\u00e9 de la Mariquina", "id": 3872079}, {"city": "Las Cardas", "id": 3884524}, {"city": "Lautaro", "id": 3883615}, {"city": "Rengo", "id": 3873441}, {"city": "Molina", "id": 3879627}, {"city": "Longavi", "id": 3882559}, {"city": "La Reina", "id": 3884806}, {"city": "La Leonera", "id": 3885471}, {"city": "Caldera", "id": 3897322}, {"city": "Retulemus", "id": 3873369}, {"city": "Puerto Natales", "id": 3874958}, {"city": "Llanquihue", "id": 3882957}, {"city": "Cabrero", "id": 3897557}, {"city": "Collipulli", "id": 3894177}, {"city": "Graneros", "id": 3888749}, {"city": "Los Pellines", "id": 3881607}, {"city": "Victoria", "id": 3868326}, {"city": "Tome", "id": 3869657}, {"city": "Nueva Imperial", "id": 3878456}, {"city": "Bulnes", "id": 3897724}, {"city": "San Carlos", "id": 3872326}, {"city": "Freirina", "id": 3889317}, {"city": "Las Barrancas", "id": 3884607}, {"city": "Vallenar", "id": 3868633}, {"city": "Purey", "id": 3874606}, {"city": "Paillaco", "id": 3877744}, {"city": "Re\u00f1aca", "id": 3873464}, {"city": "Regi\u00f3n de Tarapac\u00e1", "id": 3870116}, {"city": "Alto Hospicio", "id": 3899887}, {"city": "Frutillar Alto", "id": 3889262}, {"city": "San Jos\u00e9 de Tango", "id": 3872065}, {"city": "Curacav\u00ed", "id": 3892934}, {"city": "El Trebolar", "id": 3890212}, {"city": "La Chacrita", "id": 3886292}, {"city": "Ipinco", "id": 3887136}, {"city": "Oficina Mar\u00eda Elena", "id": 3878253}, {"city": "Francke", "id": 3889332}, {"city": "Puerto Aisen", "id": 3874997}, {"city": "Monte Patria", "id": 3879429}, {"city": "El Pe\u00f1\u00f3n", "id": 3890771}, {"city": "Gamboa", "id": 3889146}, {"city": "La Ligua", "id": 3885456}, {"city": "Pucon", "id": 3875070}, {"city": "Pitrufquen", "id": 3875746}, {"city": "Casablanca", "id": 3896410}, {"city": "Tongoicillo", "id": 3869644}, {"city": "Puerto Octay", "id": 3874951}, {"city": "Malloa", "id": 3880827}, {"city": "Lo Barnechea", "id": 3882797}, {"city": "Chacra Valpara\u00edso", "id": 3895711}, {"city": "\u00d1u\u00f1oa", "id": 3878431}, {"city": "El Quisco", "id": 3890596}, {"city": "Las Hijuelas", "id": 3884322}, {"city": "Quintero", "id": 3873983}, {"city": "Curanilahue", "id": 3892892}, {"city": "Isla de Maipo", "id": 3887072}, {"city": "Requ\u00ednoa", "id": 3873414}, {"city": "Vilcun", "id": 3868210}, {"city": "Peumos", "id": 3876367}, {"city": "Dalcahue", "id": 3892760}, {"city": "Puente Alto", "id": 3875023}, {"city": "Machali", "id": 3881102}, {"city": "Achao", "id": 3900700}, {"city": "Curaco", "id": 3892929}, {"city": "Nancagua", "id": 3879062}, {"city": "Mejillones", "id": 3880143}, {"city": "Renca", "id": 3873454}, {"city": "Futrono", "id": 3889221}, {"city": "Chonchi", "id": 3894871}, {"city": "Ca\u00f1ete", "id": 3950116}, {"city": "Quill\u00f3n", "id": 3874122}, {"city": "Quell\u00f3n", "id": 3969858}, {"city": "Puchuncav\u00ed", "id": 3875080}, {"city": "Curacaut\u00edn", "id": 3892935}, {"city": "Capellan\u00eda", "id": 3896847}, {"city": "Carahue", "id": 3896774}, {"city": "Porvenir", "id": 3875367}, {"city": "Chacarilla de Macul", "id": 3895763}, {"city": "San Joaqu\u00edn", "id": 3872139}, {"city": "Olmu\u00e9", "id": 3878075}, {"city": "El Rosal", "id": 3890485}, {"city": "La Cisterna", "id": 3886243}, {"city": "La Estancilla", "id": 3885982}, {"city": "La Calera", "id": 3886406}, {"city": "Llolleo", "id": 3882854}, {"city": "Mulchen", "id": 3879200}, {"city": "Villa Alegre", "id": 3868194}, {"city": "Combarbal\u00e1", "id": 3893962}, {"city": "Quepe", "id": 3874367}, {"city": "Lebu", "id": 3883457}, {"city": "La Herradura", "id": 3885704}, {"city": "Coelemu", "id": 3894446}, {"city": "Gorbea", "id": 3888892}, {"city": "Tongoy", "id": 3869640}, {"city": "Alerce", "id": 3900190}, {"city": "Hijuelas", "id": 3888011}, {"city": "Nogales", "id": 3878575}, {"city": "Colb\u00fan Alto", "id": 3894318}, {"city": "Loncura", "id": 3950062}, {"city": "San Jos\u00e9 de Maipo", "id": 3872073}, {"city": "Las Cabras", "id": 3884580}, {"city": "Maull\u00edn", "id": 3880302}, {"city": "Pichidegua", "id": 3876272}, {"city": "Illapel", "id": 3887344}, {"city": "Los Loros", "id": 3881895}, {"city": "Recoleta", "id": 3873636}, {"city": "R\u00edo Negro", "id": 3873116}, {"city": "Vicuna", "id": 3868308}, {"city": "Lanco", "id": 3885251}, {"city": "Villa Alhu\u00e9", "id": 3868191}, {"city": "Coltauco", "id": 3893999}, {"city": "Padre Las Casas", "id": 3877793}, {"city": "Queil\u00e9n", "id": 3874453}, {"city": "Los Muermos", "id": 3881703}, {"city": "Cha\u00f1aral", "id": 3895553}, {"city": "Hanga Roa", "id": 4030754}, {"city": "Negrete", "id": 3878898}, {"city": "Recreo", "id": 3873630}, {"city": "Teno", "id": 3869979}, {"city": "Chile Chico", "id": 3895113}, {"city": "San Pablo", "id": 3871865}, {"city": "Monte \u00c1guila", "id": 3879476}, {"city": "Freire", "id": 3889322}, {"city": "Zapallar", "id": 3867554}, {"city": "El Retamo", "id": 3890566}, {"city": "Quinta Normal", "id": 3873992}, {"city": "Do\u00f1ihue", "id": 3892272}, {"city": "Salamanca", "id": 3872594}, {"city": "Empedrado", "id": 3890121}, {"city": "Hualqui", "id": 3888523}, {"city": "M\u00e1fil", "id": 3881046}, {"city": "Farellones", "id": 3889586}, {"city": "Petorca", "id": 3876416}, {"city": "Pozo Almonte", "id": 3875235}, {"city": "Putaendo", "id": 3874570}, {"city": "San Francisco de Mostazal", "id": 3872205}, {"city": "Tiltil", "id": 3869821}, {"city": "Los \u00c1lamos", "id": 3882460}, {"city": "San Clemente", "id": 3872306}, {"city": "Neltume", "id": 3878743}, {"city": "San Rosendo", "id": 3871715}, {"city": "Quirihue", "id": 3873958}, {"city": "Olivar Bajo", "id": 3878100}, {"city": "La Palmilla", "id": 3885137}, {"city": "Paiguano", "id": 3877770}, {"city": "Catemu", "id": 3896161}, {"city": "Curepto", "id": 3892878}, {"city": "Vichuqu\u00e9n", "id": 3868339}, {"city": "Chincolco", "id": 3895018}, {"city": "Quilleco", "id": 3874141}, {"city": "Cochrane", "id": 3894483}, {"city": "Lirqu\u00e9n", "id": 3883093}, {"city": "Puerto Cisnes", "id": 3874982}, {"city": "Pica", "id": 3876353}, {"city": "Dichato", "id": 3892470}, {"city": "Contulmo", "id": 3893690}, {"city": "Canela Baja", "id": 3896946}, {"city": "Huasco", "id": 3887758}, {"city": "Playa Ancha", "id": 3875654}, {"city": "Santa Juana", "id": 3871524}, {"city": "Los Quilos", "id": 3881450}, {"city": "Maipo", "id": 3880992}, {"city": "Lo Ovalle", "id": 3882519}, {"city": "Coihaique Alto", "id": 3894423}, {"city": "San Ignacio", "id": 3872175}, {"city": "Malloco", "id": 3880825}, {"city": "Pe\u00f1ablanca", "id": 3876713}, {"city": "Lo Miranda", "id": 3882589}, {"city": "Casas de Chacabuco", "id": 3896361}, {"city": "La Estrella", "id": 3885974}, {"city": "Puerto Saavedra", "id": 3874937}, {"city": "Retiro", "id": 3873372}, {"city": "Andacollo", "id": 3899680}, {"city": "Angostura", "id": 3899611}, {"city": "La Rana", "id": 3884827}, {"city": "P\u00faa", "id": 3875124}, {"city": "Casma", "id": 3896281}, {"city": "Misquihu\u00e9", "id": 3879681}, {"city": "Montemar", "id": 3879436}, {"city": "Puerto Williams", "id": 3874926}, {"city": "Laraquete", "id": 3884823}, {"city": "Lontu\u00e9", "id": 3882530}, {"city": "Radal", "id": 3873868}, {"city": "Maitencillo", "id": 3880952}, {"city": "Taltal", "id": 3870243}, {"city": "Papudo", "id": 3877251}, {"city": "Portezuelo", "id": 3875407}, {"city": "Huech\u00fan", "id": 3887736}, {"city": "Los Ranchillos", "id": 3881433}, {"city": "Mel\u00f3n", "id": 3891046}, {"city": "Huala\u00f1\u00e9", "id": 3887788}, {"city": "San Pedro de Atacama", "id": 3871781}, {"city": "San Vicente de Taguatagua", "id": 3871276}, {"city": "Cerro Viejo", "id": 3895823}, {"city": "Nielol", "id": 3878678}, {"city": "Espejo", "id": 3889867}, {"city": "El Crucero", "id": 3891536}, {"city": "Ba\u00f1os de Colina", "id": 3898803}, {"city": "Galvarino", "id": 3889153}, {"city": "Melipeuco", "id": 3880108}, {"city": "Pillanlelbun", "id": 3875986}, {"city": "Valdivia de Paine", "id": 3868700}, {"city": "Brisas del Sol", "id": 6693593}, {"city": "Chabunco", "id": 3895816}, {"city": "Chaiten", "id": 3895642}, {"city": "Ochagav\u00eda", "id": 3878371}, {"city": "La Feria", "id": 3885958}, {"city": "San Antonio", "id": 8047985}, {"city": "Maquegua", "id": 3880590}, {"city": "Castro", "id": 3896218}, {"city": "Isl\u00f3n", "id": 3887059}, {"city": "El Salto", "id": 3890441}, {"city": "Poblaci\u00f3n Parque Forestal", "id": 3875592}, {"city": "Cha\u00f1aral", "id": 3895554}, {"city": "Puerto Bories", "id": 8030642}, {"city": "Pichil", "id": 3876261}, {"city": "El Array\u00e1n", "id": 3891940}, {"city": "Futaleufu", "id": 3889223}, {"city": "La Portada", "id": 3884937}, {"city": "Santa Teresa de Lo Ovalle", "id": 3871345}, {"city": "Chucumata", "id": 3894774}, {"city": "General Lagos Guindos", "id": 3889019}, {"city": "Balmaceda", "id": 3898880}, {"city": "Majadas", "id": 3880906}, {"city": "Palena", "id": 3877644}, {"city": "Pupelde", "id": 3874675}, {"city": "Vina del Mar", "id": 3868121}, {"city": "Santiago", "id": 3871336}, {"city": "Arica", "id": 3899361}, {"city": "Putre", "id": 3874552}, {"city": "Corral", "id": 3893516}, {"city": "Coihueco", "id": 3894406}, {"city": "Calbuco", "id": 3897334}, {"city": "Puerto Chacabuco", "id": 3950166}, {"city": "La Junta", "id": 3969755}, {"city": "Las Gaviotas", "id": 6458705}, {"city": "Ostrov Paskhi", "id": 6930873}, {"city": "Villa Presidente Frei, Nunoa, Santiago, Chile", "id": 7874740}, {"city": "Provincia de Santiago", "id": 3871332}, {"city": "Recoleta", "id": 8261417}, {"city": "Barrio Bellavista", "id": 7729816}, {"city": "Provincia de Antofagasta", "id": 3899538}, {"city": "Antofagasta", "id": 8261129}, {"city": "Vallenar", "id": 8259949}]