[{"city": "Ak-Shor", "id": 1528919}, {"city": "Ch\u00fcy", "id": 1538652}, {"city": "Ala-Archa Al\u2019plegri", "id": 8064044}, {"city": "Isfana", "id": 1222662}, {"city": "Jalal-Abad", "id": 1528249}, {"city": "Balykchy", "id": 1527004}, {"city": "Cholpon-Ata", "id": 1528512}, {"city": "Bosteri", "id": 1528646}, {"city": "Kara-Balta", "id": 1528182}, {"city": "Tokmok", "id": 1527199}, {"city": "Kalininskoe", "id": 1528211}, {"city": "Sokuluk", "id": 1527360}, {"city": "Orlovka", "id": 1527551}, {"city": "Kant", "id": 1528193}, {"city": "Bystrovka", "id": 1528606}, {"city": "Aravan", "id": 1528831}, {"city": "Uzgen", "id": 1527513}, {"city": "Kadamjay", "id": 1528336}, {"city": "Naryn Oblasty", "id": 1527590}, {"city": "At-Bashi", "id": 1528796}, {"city": "Pokrovka", "id": 1527497}, {"city": "Alga", "id": 1528856}, {"city": "Bishkek", "id": 1528334}, {"city": "Bishkek", "id": 1528675}, {"city": "Talas Oblasty", "id": 1527297}, {"city": "Talas", "id": 1527299}, {"city": "Karakol", "id": 1528121}, {"city": "Jalal-Abad Oblasty", "id": 1529778}, {"city": "Tash-Kumyr", "id": 1527260}, {"city": "Batken", "id": 1528735}, {"city": "Toktogul", "id": 1538648}, {"city": "Kyrgyz Republic", "id": 1527747}, {"city": "Osh Oblasty", "id": 1346798}, {"city": "Ak-Su", "id": 1528913}, {"city": "Talas", "id": 7649203}, {"city": "Issyk-Kul\u2019skaya Oblast\u2019", "id": 1528260}, {"city": "Kara-Chungkur", "id": 1527475}, {"city": "Ak-Chiy", "id": 1528947}, {"city": "Kyzyl-Kyshtak", "id": 1527725}, {"city": "Karavan", "id": 1528052}, {"city": "Kyzyl-Mekhnat", "id": 8139898}, {"city": "Mramornoe", "id": 8064028}, {"city": "Batken Oblasty", "id": 1463580}, {"city": "Sulyukta", "id": 1222562}, {"city": "Osh", "id": 1527534}, {"city": "Naryn", "id": 1527592}, {"city": "Kyzyl-Kyya", "id": 1527719}, {"city": "Kara Suu", "id": 1528091}, {"city": "Bazar-Korgon", "id": 1528717}, {"city": "Khaydarkan", "id": 1222635}, {"city": "Tyup", "id": 1527121}, {"city": "Teploklyuchenka", "id": 1527232}, {"city": "Suzak", "id": 1527317}, {"city": "Chuy", "id": 1527338}, {"city": "Sosnovka", "id": 1527351}, {"city": "Pokrovka", "id": 1527496}, {"city": "Leninpol", "id": 1527688}, {"city": "Massy", "id": 1527689}, {"city": "Lebedinovka", "id": 1527690}, {"city": "Kochkor", "id": 1527902}, {"city": "Kirovskoye", "id": 1527919}, {"city": "Kazarman", "id": 1528005}, {"city": "Karavan", "id": 1528053}, {"city": "Kanysh-Kyya", "id": 1528190}, {"city": "Kaindy", "id": 1528234}, {"city": "Kadzhi-Say", "id": 1528241}, {"city": "Ivanovka", "id": 1528252}, {"city": "Ivanovo-Alekseyevka", "id": 1528253}, {"city": "Gulcha", "id": 1528320}, {"city": "Chayek", "id": 1528566}, {"city": "Bokombayevskoye", "id": 1528666}, {"city": "Belovodskoye", "id": 1528702}, {"city": "Baetov", "id": 1528766}, {"city": "Ala-Buka", "id": 1528875}, {"city": "Uch-Terek", "id": 8134212}, {"city": "Kara-Kulja", "id": 8145969}]